CustomModules/__init__.py
CustomModules/app_translation.py
CustomModules/bitmap_handler.py
CustomModules/bot_directory.py
CustomModules/database_handler.py
CustomModules/googletrans.py
CustomModules/invite_tracker.py
CustomModules/killswitch.py
CustomModules/libretrans.py
CustomModules/log_handler.py
CustomModules/patchnotes.py
CustomModules/private_voice.py
CustomModules/py.typed
CustomModules/random_usernames.py
CustomModules/stat_dock.py
CustomModules/steam.py
CustomModules/steam_charts.py
CustomModules/twitch.py
custommodules-3.1.1.dist-info/licenses/LICENSE.txt
custommodules-3.1.1.dist-info/METADATA
custommodules-3.1.1.dist-info/WHEEL
custommodules-3.1.1.dist-info/top_level.txt
custommodules-3.1.1.dist-info/RECORD
