Metadata-Version: 2.4
Name: CustomModules
Version: 3.1.1
Summary: A collection of custom Python modules for Discord bots and utilities
Home-page: https://github.com/Serpensin/CustomModules-Python
Author: Serpensin
License-Expression: AGPL-3.0-or-later
Project-URL: Homepage, https://github.com/Serpensin/CustomModules-Python
Project-URL: Bug Reports, https://github.com/Serpensin/CustomModules-Python/issues
Project-URL: Source, https://github.com/Serpensin/CustomModules-Python
Keywords: discord,bot,utilities,modules,custom
Classifier: Development Status :: 5 - Production/Stable
Classifier: Intended Audience :: Developers
Classifier: Operating System :: OS Independent
Classifier: Programming Language :: Python :: 3
Classifier: Programming Language :: Python :: 3.10
Classifier: Programming Language :: Python :: 3.11
Classifier: Programming Language :: Python :: 3.12
Classifier: Programming Language :: Python :: 3.13
Classifier: Topic :: Software Development :: Libraries :: Python Modules
Classifier: Topic :: Communications :: Chat
Requires-Python: >=3.10,<3.14
License-File: LICENSE.txt
Provides-Extra: apptranslation
Requires-Dist: discord.py>=2.3.0; extra == "apptranslation"
Provides-Extra: bitmaphandler
Provides-Extra: botdirectory
Requires-Dist: aiohttp>=3.9.3; extra == "botdirectory"
Provides-Extra: databasehandler
Requires-Dist: aiosqlite>=0.19.0; extra == "databasehandler"
Requires-Dist: aiomysql>=0.2.0; extra == "databasehandler"
Requires-Dist: asyncpg>=0.29.0; extra == "databasehandler"
Requires-Dist: psycopg[binary,pool]>=3.1.0; extra == "databasehandler"
Requires-Dist: motor>=3.3.0; extra == "databasehandler"
Provides-Extra: googletrans
Requires-Dist: google-cloud-translate>=3.15.3; extra == "googletrans"
Provides-Extra: invitetracker
Requires-Dist: discord.py>=2.3.0; extra == "invitetracker"
Provides-Extra: killswitch
Requires-Dist: aiohttp>=3.9.3; extra == "killswitch"
Requires-Dist: html2text>=2024.2.26; extra == "killswitch"
Requires-Dist: beautifulsoup4>=4.12.3; extra == "killswitch"
Provides-Extra: libretrans
Requires-Dist: aiohttp>=3.9.3; extra == "libretrans"
Requires-Dist: aiofiles>=25.1.0; extra == "libretrans"
Provides-Extra: loghandler
Requires-Dist: colorama>=0.4.6; extra == "loghandler"
Provides-Extra: patchnotes
Requires-Dist: aiohttp>=3.9.3; extra == "patchnotes"
Requires-Dist: html2text>=2024.2.26; extra == "patchnotes"
Requires-Dist: beautifulsoup4>=4.12.3; extra == "patchnotes"
Provides-Extra: privatevoice
Requires-Dist: discord.py>=2.3.0; extra == "privatevoice"
Provides-Extra: randomusernames
Provides-Extra: statdock
Requires-Dist: discord.py>=2.3.0; extra == "statdock"
Requires-Dist: pytz>=2024.2; extra == "statdock"
Provides-Extra: steam
Requires-Dist: aiohttp>=3.9.3; extra == "steam"
Requires-Dist: beautifulsoup4>=4.12.3; extra == "steam"
Provides-Extra: steamcharts
Requires-Dist: aiohttp>=3.9.3; extra == "steamcharts"
Requires-Dist: beautifulsoup4>=4.12.3; extra == "steamcharts"
Provides-Extra: twitch
Requires-Dist: aiohttp>=3.9.3; extra == "twitch"
Requires-Dist: requests>=2.31.0; extra == "twitch"
Provides-Extra: all
Requires-Dist: aiofiles>=25.1.0; extra == "all"
Requires-Dist: aiohttp>=3.9.3; extra == "all"
Requires-Dist: aiomysql>=0.2.0; extra == "all"
Requires-Dist: aiosqlite>=0.19.0; extra == "all"
Requires-Dist: asyncpg>=0.29.0; extra == "all"
Requires-Dist: beautifulsoup4>=4.12.3; extra == "all"
Requires-Dist: colorama>=0.4.6; extra == "all"
Requires-Dist: discord.py>=2.3.0; extra == "all"
Requires-Dist: google-cloud-translate>=3.15.3; extra == "all"
Requires-Dist: html2text>=2024.2.26; extra == "all"
Requires-Dist: motor>=3.3.0; extra == "all"
Requires-Dist: psycopg[binary,pool]>=3.1.0; extra == "all"
Requires-Dist: pytz>=2024.2; extra == "all"
Requires-Dist: requests>=2.31.0; extra == "all"
Dynamic: home-page
Dynamic: license-file
Dynamic: provides-extra
Dynamic: requires-python
